odoo10_addon_mrp_mto_with_stock_purchase-10.0.1.0.0.99.dev7-py3.8-nspkg.pth
odoo/addons/mrp_mto_with_stock_purchase/README.rst
odoo/addons/mrp_mto_with_stock_purchase/__init__.py
odoo/addons/mrp_mto_with_stock_purchase/__manifest__.py
odoo/addons/mrp_mto_with_stock_purchase/i18n/de.po
odoo/addons/mrp_mto_with_stock_purchase/i18n/mrp_mto_with_stock_purchase.pot
odoo/addons/mrp_mto_with_stock_purchase/models/__init__.py
odoo/addons/mrp_mto_with_stock_purchase/models/mrp_production.py
odoo/addons/mrp_mto_with_stock_purchase/readme/CONFIGURE.rst
odoo/addons/mrp_mto_with_stock_purchase/readme/CONTRIBUTORS.rst
odoo/addons/mrp_mto_with_stock_purchase/readme/DESCRIPTION.rst
odoo/addons/mrp_mto_with_stock_purchase/readme/USAGE.rst
odoo/addons/mrp_mto_with_stock_purchase/static/description/icon.png
odoo/addons/mrp_mto_with_stock_purchase/static/description/index.html
odoo10_addon_mrp_mto_with_stock_purchase-10.0.1.0.0.99.dev7.dist-info/METADATA
odoo10_addon_mrp_mto_with_stock_purchase-10.0.1.0.0.99.dev7.dist-info/WHEEL
odoo10_addon_mrp_mto_with_stock_purchase-10.0.1.0.0.99.dev7.dist-info/namespace_packages.txt
odoo10_addon_mrp_mto_with_stock_purchase-10.0.1.0.0.99.dev7.dist-info/top_level.txt
odoo10_addon_mrp_mto_with_stock_purchase-10.0.1.0.0.99.dev7.dist-info/RECORD
