Metadata-Version: 2.1
Name: odoo10-addon-mrp-mto-with-stock-purchase
Version: 10.0.1.0.0.99.dev7
Summary: Module needed to make mrp_mto_with_stock module compatible with purchase module.
Home-page: https://github.com/OCA/manufacture
Author: Akretion, Odoo Community Association (OCA)
Author-email: support@odoo-community.org
License: AGPL-3
Platform: UNKNOWN
Classifier: Programming Language :: Python
Classifier: Framework :: Odoo
Classifier: Framework :: Odoo :: 10.0
Classifier: License :: OSI Approved :: GNU Affero General Public License v3
Requires-Python: ~=2.7
Requires-Dist: odoo10-addon-mrp-mto-with-stock
Requires-Dist: odoo <10.1dev,>=10.0
